como/__init__.py
como/component_distributions.py
como/logistic_regression.py
como/logistic_ser.py
como/logistic_susie.py
como/mococomo.py
como/twococomo.py
como/utils.py
como_ebnm-0.0.14.dist-info/LICENSE.txt
como_ebnm-0.0.14.dist-info/METADATA
como_ebnm-0.0.14.dist-info/WHEEL
como_ebnm-0.0.14.dist-info/top_level.txt
como_ebnm-0.0.14.dist-info/RECORD
